[
  {
    "qid":44,
    "id":1416,
    "category":"Communication & Chat",
    "question":"Can I mute a conversation using Ambel?"
  },
  {
    "qid":49,
    "id":1436,
    "category":"Communication & Chat",
    "question":"What if I need to report inappropriate messages on Ambel?"
  },
  {
    "qid":65,
    "id":1458,
    "category":"Communication & Chat",
    "question":"What’s the best way to download chat history if I’m new here?"
  },
  {
    "qid":102,
    "id":1401,
    "category":"Communication & Chat",
    "question":"Can I translate chat messages step by step?"
  },
  {
    "qid":111,
    "id":1498,
    "category":"Communication & Chat",
    "question":"When can I rate a chat interaction if I’m new here?"
  },
  {
    "qid":155,
    "id":1332,
    "category":"Communication & Chat",
    "question":"How do I get reply notifications on Ambel?"
  },
  {
    "qid":177,
    "id":1431,
    "category":"Communication & Chat",
    "question":"How do I report inappropriate messages on Ambel?"
  },
  {
    "qid":179,
    "id":1350,
    "category":"Communication & Chat",
    "question":"Is it possible to see when a practitioner is typing step by step?"
  },
  {
    "qid":192,
    "id":1500,
    "category":"Communication & Chat",
    "question":"What’s the best way to rate a chat interaction without contacting support?"
  },
  {
    "qid":195,
    "id":1384,
    "category":"Communication & Chat",
    "question":"Can I attach legal documents for review from my computer?"
  },
  {
    "qid":206,
    "id":1302,
    "category":"Communication & Chat",
    "question":"Who can help me send photos or files in chat step by step?"
  },
  {
    "qid":207,
    "id":1333,
    "category":"Communication & Chat",
    "question":"How do I get reply notifications without contacting support?"
  },
  {
    "qid":228,
    "id":1427,
    "category":"Communication & Chat",
    "question":"Who can help me block a practitioner quickly?"
  },
  {
    "qid":246,
    "id":1345,
    "category":"Communication & Chat",
    "question":"How can I see when a practitioner is typing from my phone?"
  },
  {
    "qid":270,
    "id":1422,
    "category":"Communication & Chat",
    "question":"Can I block a practitioner on Ambel?"
  },
  {
    "qid":272,
    "id":1407,
    "category":"Communication & Chat",
    "question":"What’s the best way to translate chat messages from my phone?"
  },
  {
    "qid":295,
    "id":1371,
    "category":"Communication & Chat",
    "question":"How can I share lab reports securely step by step?"
  },
  {
    "qid":298,
    "id":1403,
    "category":"Communication & Chat",
    "question":"When can I translate chat messages from my computer?"
  },
  {
    "qid":327,
    "id":1354,
    "category":"Communication & Chat",
    "question":"How do I schedule a message to send later on Ambel?"
  },
  {
    "qid":348,
    "id":1388,
    "category":"Communication & Chat",
    "question":"When can I switch from chat to video call using Ambel?"
  },
  {
    "qid":360,
    "id":1301,
    "category":"Communication & Chat",
    "question":"What if I need to send photos or files in chat without contacting support?"
  },
  {
    "qid":362,
    "id":1385,
    "category":"Communication & Chat",
    "question":"What’s the best way to attach legal documents for review if I’m new here?"
  },
  {
    "qid":365,
    "id":1466,
    "category":"Communication & Chat",
    "question":"Is it possible to allow my family to view messages from my computer?"
  },
  {
    "qid":376,
    "id":1361,
    "category":"Communication & Chat",
    "question":"How can I schedule a message to send later as a first-time user?"
  },
  {
    "qid":412,
    "id":1499,
    "category":"Communication & Chat",
    "question":"When can I rate a chat interaction without contacting support?"
  },
  {
    "qid":417,
    "id":1417,
    "category":"Communication & Chat",
    "question":"Can I mute a conversation step by step?"
  },
  {
    "qid":418,
    "id":1496,
    "category":"Communication & Chat",
    "question":"What if I need to escalate an issue in chat as a first-time user?"
  },
  {
    "qid":433,
    "id":1446,
    "category":"Communication & Chat",
    "question":"Where can I archive a conversation through the Ambel app?"
  },
  {
    "qid":435,
    "id":1430,
    "category":"Communication & Chat",
    "question":"What if I need to block a practitioner step by step?"
  },
  {
    "qid":505,
    "id":1429,
    "category":"Communication & Chat",
    "question":"What if I need to block a practitioner as a first-time user?"
  },
  {
    "qid":581,
    "id":1454,
    "category":"Communication & Chat",
    "question":"What if I need to download chat history through the Ambel app?"
  },
  {
    "qid":593,
    "id":1355,
    "category":"Communication & Chat",
    "question":"What’s the best way to schedule a message to send later from my computer?"
  },
  {
    "qid":638,
    "id":1304,
    "category":"Communication & Chat",
    "question":"Where can I send photos or files in chat using Ambel?"
  },
  {
    "qid":706,
    "id":1348,
    "category":"Communication & Chat",
    "question":"Where can I see when a practitioner is typing through the Ambel app?"
  },
  {
    "qid":729,
    "id":1442,
    "category":"Communication & Chat",
    "question":"How do I archive a conversation on Ambel?"
  },
  {
    "qid":733,
    "id":1444,
    "category":"Communication & Chat",
    "question":"Is it possible to archive a conversation quickly?"
  },
  {
    "qid":771,
    "id":1494,
    "category":"Communication & Chat",
    "question":"Is it possible to escalate an issue in chat if I’m new here?"
  },
  {
    "qid":772,
    "id":1402,
    "category":"Communication & Chat",
    "question":"Can I translate chat messages through the Ambel app?"
  },
  {
    "qid":792,
    "id":1331,
    "category":"Communication & Chat",
    "question":"When can I request a callback from a practitioner as a first-time user?"
  },
  {
    "qid":797,
    "id":1435,
    "category":"Communication & Chat",
    "question":"Do you support report inappropriate messages using Ambel?"
  },
  {
    "qid":808,
    "id":1290,
    "category":"Communication & Chat",
    "question":"When can I chat with a practitioner before booking from my computer?"
  },
  {
    "qid":816,
    "id":1372,
    "category":"Communication & Chat",
    "question":"What’s the best way to share lab reports securely from my phone?"
  },
  {
    "qid":844,
    "id":1461,
    "category":"Communication & Chat",
    "question":"Is it possible to download chat history through the Ambel app?"
  },
  {
    "qid":869,
    "id":1437,
    "category":"Communication & Chat",
    "question":"What if I need to report inappropriate messages through the Ambel app?"
  },
  {
    "qid":888,
    "id":1423,
    "category":"Communication & Chat",
    "question":"Where can I block a practitioner quickly?"
  },
  {
    "qid":898,
    "id":1447,
    "category":"Communication & Chat",
    "question":"Can I archive a conversation without contacting support?"
  },
  {
    "qid":966,
    "id":1380,
    "category":"Communication & Chat",
    "question":"What if I need to attach legal documents for review step by step?"
  },
  {
    "qid":973,
    "id":1448,
    "category":"Communication & Chat",
    "question":"Can I archive a conversation step by step?"
  },
  {
    "qid":1041,
    "id":1491,
    "category":"Communication & Chat",
    "question":"How do I escalate an issue in chat step by step?"
  }
]